metaindexmanager/__init__.py
metaindexmanager/clipboard.py
metaindexmanager/command.py
metaindexmanager/commandinput.py
metaindexmanager/commands.py
metaindexmanager/detailpanel.py
metaindexmanager/docpanel.py
metaindexmanager/editorpanel.py
metaindexmanager/filepanel.py
metaindexmanager/helppanel.py
metaindexmanager/keyhelppanel.py
metaindexmanager/layouts.py
metaindexmanager/main.py
metaindexmanager/panel.py
metaindexmanager/shared.py
metaindexmanager/utils.py
metaindexmanager/version.py
metaindexmanager/docs/metaindexmanager.html
metaindexmanager-0.9.0.data/data/share/applications/metaindexmanager.desktop
metaindexmanager-0.9.0.data/data/share/doc/metaindexmanager/mtattach.sh
metaindexmanager-0.9.0.data/data/share/man/man1/metaindexmanager.1
metaindexmanager-0.9.0.dist-info/LICENSE
metaindexmanager-0.9.0.dist-info/METADATA
metaindexmanager-0.9.0.dist-info/WHEEL
metaindexmanager-0.9.0.dist-info/entry_points.txt
metaindexmanager-0.9.0.dist-info/top_level.txt
metaindexmanager-0.9.0.dist-info/RECORD
