Metadata-Version: 2.1
Name: metaindexmanager
Version: 0.9.0
Summary: Console UI to browse metaindex file(s).
Home-page: https://vonshednob.cc/metaindexmanager
Author: R
Author-email: contact+metaindexmanager@vonshednob.cc
License: UNKNOWN
Platform: UNKNOWN
Classifier: Development Status :: 3 - Alpha
Classifier: Environment :: Console :: Curses
Classifier: Intended Audience :: End Users/Desktop
Classifier: License :: OSI Approved :: MIT License
Classifier: Natural Language :: English
Classifier: Programming Language :: Python :: 3
Requires-Python: >=3.8
License-File: LICENSE
Requires-Dist: metaindex (>=1.3.0)
Requires-Dist: cursedspace (>=1.5.0)
